bam_reheader/__init__.py
bam_reheader/__main__.py
bam_reheader/main.py
bam_reheader-0.39.dist-info/LICENSE
bam_reheader-0.39.dist-info/METADATA
bam_reheader-0.39.dist-info/WHEEL
bam_reheader-0.39.dist-info/entry_points.txt
bam_reheader-0.39.dist-info/top_level.txt
bam_reheader-0.39.dist-info/RECORD
